easy_s3/__init__.py
easy_s3-1.0.7.dist-info/LICENSE
easy_s3-1.0.7.dist-info/METADATA
easy_s3-1.0.7.dist-info/WHEEL
easy_s3-1.0.7.dist-info/top_level.txt
easy_s3-1.0.7.dist-info/RECORD
