Metadata-Version: 2.1
Name: easy-s3
Version: 1.0.7
Summary: This package helps you use S3 easily.
Home-page: https://github.com/da-huin/easy_s3
Author: JunYeong Park
Author-email: dahuin000@gmail.com
License: MIT
Download-URL: https://github.com/da-huin/easy_s3/archive/master.zip
Platform: UNKNOWN
Classifier: Programming Language :: Python :: 3
Requires-Dist: boto3
